Workbook

Sheet Trial Balance
A1: TechServe India Pvt Ltd
A2: Trial Balance — Month Ended 31 March 2025
A4: Account Code | B4: Account Name | C4: Category | D4: Opening Balance (₹) | E4: Transactions (₹) | F4: Closing Balance (₹) | G4: Notes
A5: 1001 | B5: Cash & Bank — HDFC Current A/c | C5: Current Asset | D5: 8500000 | E5: 3200000 | F5: =D5+E5 -> 11700000 | G5: Reconciled with bank statement
A6: 1002 | B6: Cash & Bank — Petty Cash | C6: Current Asset | D6: 150000 | E6: -45000 | F6: =D6+E6 -> 105000 | G6: Petty cash vouchers verified
A7: 1003 | B7: Accounts Receivable | C7: Current Asset | D7: 18700000 | E7: 4600000 | F7: =D7+E7 -> 23300000 | G7: Ageing reviewed; no new provisions
A8: 1004 | B8: Advance to Employees | C8: Current Asset | D8: 320000 | E8: -80000 | F8: =D8+E8 -> 240000 | G8: Recovery per HR schedule
A9: 1005 | B9: Prepaid Expenses | C9: Current Asset | D9: 900000 | E9: -150000 | F9: =D9+E9 -> 750000 | G9: Insurance & subscriptions amortised
A10: 1006 | B10: GST Input Tax Credit Receivable | C10: Current Asset | D10: 1200000 | E10: 350000 | F10: =D10+E10 -> 1550000 | G10: Reconciled with GSTR-2B
A11: 1007 | B11: Property, Plant & Equipment (Gross) | C11: Fixed Asset | D11: 42000000 | E11: 0 | F11: =D11+E11 -> 42000000 | G11: No additions this month
A12: 1008 | B12: Accumulated Depreciation | C12: Fixed Asset | D12: -12500000 | E12: -350000 | F12: =D12+E12 -> -12850000 | G12: Monthly dep. @ SLM rates
A13: 1009 | B13: Right-of-Use Asset (Leased Office) | C13: Fixed Asset | D13: 6800000 | E13: -120000 | F13: =D13+E13 -> 6680000 | G13: Ind AS 116 — lease amortisation
A14: 2001 | B14: Accounts Payable | C14: Current Liability | D14: -4200000 | E14: -680000 | F14: =D14+E14 -> -4880000 | G14: Vendor invoices approved
A15: 2002 | B15: Salaries & Bonus Payable | C15: Current Liability | D15: -1800000 | E15: -2850000 | F15: =D15+E15 -> -4650000 | G15: March payroll processed 31-Mar
A16: 2003 | B16: GST Payable (Output) | C16: Current Liability | D16: -2100000 | E16: -1350000 | F16: =D16+E16 -> -3450000 | G16: GSTR-1 filed; net liability confirmed
... A42: 8001 | B42: Income Tax Provision | C42: Tax | D42: 0 | E42: 312000 | F42: =D42+E42 -> 312000 | G42: 25% of PBT estimate
A43: TOTAL (Debit = Credit check) | D43: =SUM(D5:D42) -> -300000 | E43: =SUM(E5:E42) -> -2295000 | F43: =SUM(F5:F42) -> -2595000 | G43: Should be ₹0 if balanced
A45: Colour Legend — Finance Standard
A46: ■ Blue text | B46: Hardcoded inputs
A47: ■ Black text | B47: Formula / calculated
A48: ■ Green text | B48: Cross-sheet link

Sheet P&L Statement
A1: TechServe India Pvt Ltd
A2: Statement of Profit & Loss — Month Ended 31 March 2025
A4: Line Item | B4: Account Code(s) | C4: March 2025 (₹) | D4: % of Revenue
A5: I. REVENUE
A6: IT Services Revenue — Domestic | B6: 4001 | C6: =-1*(SUMIF('Trial Balance'!A$5:A$42,"4001",'Trial Balance'!E$5:E$42)) -> 7500000 | D6: =IF(C10<>0,C6/C10,0) -> 0.57034221
A7: IT Services Revenue — Export | B7: 4002 | C7: =-1*(SUMIF('Trial Balance'!A$5:A$42,"4002",'Trial Balance'!E$5:E$42)) -> 4200000 | D7: =IF(C10<>0,C7/C10,0) -> 0.31939163
A8: Software Licensing Revenue | B8: 4003 | C8: =-1*(SUMIF('Trial Balance'!A$5:A$42,"4003",'Trial Balance'!E$5:E$42)) -> 800000 | D8: =IF(C10<>0,C8/C10,0) -> 0.060836502
A9: Consulting & Advisory Fees | B9: 4004 | C9: =-1*(SUMIF('Trial Balance'!A$5:A$42,"4004",'Trial Balance'!E$5:E$42)) -> 650000 | D9: =IF(C10<>0,C9/C10,0) -> 0.049429658
A10: TOTAL REVENUE | C10: =SUM(C6,C7,C8,C9) -> 13150000 | D10: =IF(C10<>0,C10/C10,0) -> 1
A12: II. COST OF GOODS SOLD (COGS)
A13: Cost of Delivery — Salaries | B13: 5001 | C13: =SUMIF('Trial Balance'!A$5:A$42,"5001",'Trial Balance'!E$5:E$42) -> 4200000 | D13: =IF(C10<>0,C13/C10,0) -> 0.31939163
A14: Subcontracting Charges | B14: 5002 | C14: =SUMIF('Trial Balance'!A$5:A$42,"5002",'Trial Balance'!E$5:E$42) -> 950000 | D14: =IF(C10<>0,C14/C10,0) -> 0.072243346
A15: Cloud Infra & Hosting | B15: 5003 | C15: =SUMIF('Trial Balance'!A$5:A$42,"5003",'Trial Balance'!E$5:E$42) -> 620000 | D15: =IF(C10<>0,C15/C10,0) -> 0.047148289
A16: Software Licenses (COGS) | B16: 5004 | C16: =SUMIF('Trial Balance'!A$5:A$42,"5004",'Trial Balance'!E$5:E$42) -> 180000 | D16: =IF(C10<>0,C16/C10,0) -> 0.013688213
A17: TOTAL COGS | C17: =SUM(C13,C14,C15,C16) -> 5950000 | D17: =IF(C10<>0,C17/C10,0) -> 0.45247148
A18: GROSS PROFIT | C18: =C10-C17 -> 7200000 | D18: =IF(C10<>0,C18/C10,0) -> 0.54752852
A19: Gross Margin % | D19: =IF(C10<>0,C18/C10,0) -> 0.54752852
A21: III. OPERATING EXPENSES (OPEX)
A22: Salaries — Support & Admin | B22: 6001 | C22: =SUMIF('Trial Balance'!A$5:A$42,"6001",'Trial Balance'!E$5:E$42) -> 1450000 | D22: =IF(C10<>0,C22/C10,0) -> 0.11026616
A23: Rent — Bangalore HQ | B23: 6002 | C23: =SUMIF('Trial Balance'!A$5:A$42,"6002",'Trial Balance'!E$5:E$42) -> 480000 | D23: =IF(C10<>0,C23/C10,0) -> 0.036501901
A24: Depreciation & Amortisation | B24: 6003 | C24: =SUMIF('Trial Balance'!A$5:A$42,"6003",'Trial Balance'!E$5:E$42) -> 470000 | D24: =IF(C10<>0,C24/C10,0) -> 0.035741445
A25: Internet & Telecom | B25: 6004 | C25: =SUMIF('Trial Balance'!A$5:A$42,"6004",'Trial Balance'!E$5:E$42) -> 85000 | D25: =IF(C10<>0,C25/C10,0) -> 0.0064638783
A26: Travel & Conveyance | B26: 6005 | C26: =SUMIF('Trial Balance'!A$5:A$42,"6005",'Trial Balance'!E$5:E$42) -> 120000 | D26: =IF(C10<>0,C26/C10,0) -> 0.0091254753
A27: Marketing & Business Dev | B27: 6006 | C27: =SUMIF('Trial Balance'!A$5:A$42,"6006",'Trial Balance'!E$5:E$42) -> 95000 | D27: =IF(C10<>0,C27/C10,0) -> 0.0072243346
A28: Professional Fees (Audit/Legal) | B28: 6007 | C28: =SUMIF('Trial Balance'!A$5:A$42,"6007",'Trial Balance'!E$5:E$42) -> 150000 | D28: =IF(C10<>0,C28/C10,0) -> 0.011406844
A29: Office & Admin Expenses | B29: 6008 | C29: =SUMIF('Trial Balance'!A$5:A$42,"6008",'Trial Balance'!E$5:E$42) -> 65000 | D29: =IF(C10<>0,C29/C10,0) -> 0.0049429658
A30: TOTAL OPEX | C30: =SUM(C22,C23,C24,C25,C26,C27,C28,C29) -> 2915000 | D30: =IF(C10<>0,C30/C10,0) -> 0.221673
A31: EBITDA | C31: =C18-C30 -> 4285000 | D31: =IF(C10<>0,C31/C10,0) -> 0.32585551
A32: EBITDA Margin % | D32: =IF(C10<>0,C31/C10,0) -> 0.32585551
A34: IV. OTHER INCOME / (EXPENSE)
A35: Forex Gain (Realised) | B35: 7001 | C35: =-1*(SUMIF('Trial Balance'!A$5:A$42,"7001",'Trial Balance'!E$5:E$42)) -> 85000 | D35: =IF(C10<>0,C35/C10,0) -> 0.0064638783
A36: Bank Charges & Interest | B36: 7002 | C36: =SUMIF('Trial Balance'!A$5:A$42,"7002",'Trial Balance'!E$5:E$42) -> 28000 | D36: =IF(C10<>0,C36/C10,0) -> 0.0021292776
A37: NET OTHER INCOME | C37: =SUM(C35,C36) -> 113000 | D37: =IF(C10<>0,C37/C10,0) -> 0.0085931559
A39: PROFIT BEFORE TAX (PBT) | C39: =C31+C37 -> 4398000 | D39: =IF(C10<>0,C39/C10,0) -> 0.33444867
A40: PBT Margin % | D40: =IF(C10<>0,C39/C10,0) -> 0.33444867
A41: Income Tax Provision (25%) | B41: 8001 | C41: =SUMIF('Trial Balance'!A$5:A$42,"8001",'Trial Balance'!E$5:E$42) -> 312000 | D41: =IF(C10<>0,C41/C10,0) -> 0.023726236
A42: PROFIT AFTER TAX (PAT) | C42: =C39-SUM(C41) -> 4086000 | D42: =IF(C10<>0,C42/C10,0) -> 0.31072243
A43: PAT Margin % | D43: =IF(C10<>0,C42/C10,0) -> 0.31072243

Sheet Budget vs Actuals
A1: TechServe India Pvt Ltd
A2: Budget vs Actuals — Month Ended 31 March 2025
A3: Favourable variances shown in GREEN | Unfavourable variances shown in RED
A4: # | B4: Line Item | C4: Budget (₹) | D4: Actuals (₹) | E4: Variance (₹) | F4: Variance (%) | G4: Analyst Commentary
A5: 1 | B5: Total Revenue | C5: 13500000 | D5: 13150000 | E5: =D5-C5 -> -350000 | F5: =IF(C5<>0,(D5-C5)/C5,0) -> -0.025925926 | G5: Revenue ₹3.5L below budget; export billing delayed by 2 days into April — timing difference, not a loss.
A6: 2 | B6: Cost of Delivery — Salaries | C6: 4000000 | D6: 4200000 | E6: =D6-C6 -> 200000 | F6: =IF(C6<>0,(D6-C6)/C6,0) -> 0.05 | G6: ₹2.0L over budget due to one additional contract engineer onboarded mid-month; approved by CTO.
A7: 3 | B7: Subcontracting Charges | C7: 800000 | D7: 950000 | E7: =D7-C7 -> 150000 | F7: =IF(C7<>0,(D7-C7)/C7,0) -> 0.1875 | G7: ₹1.5L adverse; escalated to vendor — dispute on scope creep; credit note expected in April.
A8: 4 | B8: Cloud Infra & Hosting | C8: 550000 | D8: 620000 | E8: =D8-C8 -> 70000 | F8: =IF(C8<>0,(D8-C8)/C8,0) -> 0.12727273 | G8: ₹0.7L over; spike in AWS data-transfer costs linked to client UAT load testing — non-recurring.
A9: 5 | B9: Gross Profit | C9: 8150000 | D9: 7380000 | E9: =D9-C9 -> -770000 | F9: =IF(C9<>0,(D9-C9)/C9,0) -> -0.094478528 | G9: GP ₹7.7L below budget; driven by revenue shortfall + cost overruns above. Margin at 56.1% vs 60.4% budgeted.
A10: 6 | B10: Salaries — Support & Admin | C10: 1300000 | D10: 1450000 | E10: =D10-C10 -> 150000 | F10: =IF(C10<>0,(D10-C10)/C10,0) -> 0.11538462 | G10: ₹1.5L over budget; one-time retention bonus paid to two senior analysts per MD approval on 28-Mar.
A11: 7 | B11: Travel & Conveyance | C11: 80000 | D11: 120000 | E11: =D11-C11 -> 40000 | F11: =IF(C11<>0,(D11-C11)/C11,0) -> 0.5 | G11: ₹0.4L over; senior BD team attended ISC West conference in Mumbai — pipeline impact: 2 RFPs received.
A12: 8 | B12: Marketing & Business Dev | C12: 120000 | D12: 95000 | E12: =D12-C12 -> -25000 | F12: =IF(C12<>0,(D12-C12)/C12,0) -> -0.20833333 | G12: ₹0.25L favourable; LinkedIn campaign paused mid-month for creative refresh; spend resumes in April.
A13: 9 | B13: EBITDA | C13: 6650000 | D13: 5715000 | E13: =D13-C13 -> -935000 | F13: =IF(C13<>0,(D13-C13)/C13,0) -> -0.1406015 | G13: EBITDA 14% below budget; combination of revenue delay + salary overrun. Management action required on Q1 close.
A14: 10 | B14: Income Tax Provision | C14: 350000 | D14: 312000 | E14: =D14-C14 -> -38000 | F14: =IF(C14<>0,(D14-C14)/C14,0) -> -0.10857143 | G14: ₹0.38L favourable; lower PBT vs budget results in reduced provision. Advance tax deposit adjusted accordingly.
A15: 11 | B15: Profit After Tax (PAT) | C15: 1200000 | D15: 980000 | E15: =D15-C15 -> -220000 | F15: =IF(C15<>0,(D15-C15)/C15,0) -> -0.18333333 | G15: PAT ₹2.2L below budget (18.3% adverse). Primary drivers: ① revenue timing ② retention bonus. Both one-time.

Sheet Close Checklist
A1: TechServe India Pvt Ltd
A2: Month-End Close Checklist — March 2025
A4: # | B4: Close Task | C4: Owner | D4: Target Date | E4: Status | F4: Notes / Evidence
A5: 1 | B5: Obtain bank statement — HDFC Current A/c | C5: Finance Analyst | D5: 28-Mar | E5: ✅ Complete | F5: Statement downloaded; matched to GL balance ₹1,17,05,000
A6: 2 | B6: Perform bank reconciliation — HDFC Current A/c | C6: Finance Analyst | D6: 29-Mar | E6: ✅ Complete | F6: 2 timing differences identified; cleared by 31-Mar
A7: 3 | B7: Post month-end accruals (salaries, rent, utilities) | C7: Finance Analyst | D7: 31-Mar | E7: ✅ Complete | F7: JV #MAR-2025-001 posted; approved by Finance Manager
A8: 4 | B8: Post depreciation journal entry | C8: Finance Analyst | D8: 31-Mar | E8: ✅ Complete | F8: PP&E ₹3.50L + ROU asset ₹1.20L — as per asset register
A9: 5 | B9: Confirm revenue recognition — domestic invoices | C9: AR Analyst | D9: 31-Mar | E9: ✅ Complete | F9: 3 invoices confirmed; milestones sign-off from PMs received
A10: 6 | B10: Confirm revenue recognition — export (forex) | C10: AR Analyst | D10: 31-Mar | E10: ✅ Complete | F10: USD 49,500 converted @ RBI rate ₹84.85; bank advice on file
A11: 7 | B11: Review open Purchase Orders > ₹50,000 | C11: Procurement Lead | D11: 29-Mar | E11: ✅ Complete | F11: 4 POs reviewed; 1 PO for ₹1.8L accrued; vendor confirmation awaited
A12: 8 | B12: Confirm GST Output Tax Liability (GSTR-1) | C12: Tax Analyst | D12: 31-Mar | E12: ✅ Complete | F12: GSTR-1 auto-populated; output tax ₹13.50L reconciled with GL
A13: 9 | B13: Reconcile GST Input Credit (GSTR-2B vs GL) | C13: Tax Analyst | D13: 31-Mar | E13: ✅ Complete | F13: ITC ₹12.00L + ₹3.50L new — mismatch of ₹18K flagged to vendor
A14: 10 | B14: TDS deducted and payable confirmed | C14: Tax Analyst | D14: 31-Mar | E14: ✅ Complete | F14: TDS ₹2.80L payable; challan to be filed by 7-Apr
A15: 11 | B15: Review advance from customers — revenue recognition | C15: Finance Manager | D15: 31-Mar | E15: ✅ Complete | F15: ₹5.00L milestone revenue recognised from advance account
A16: 12 | B16: Intercompany reconciliation (if applicable) | C16: Finance Analyst | D16: 31-Mar | E16: N/A | F16: No interco transactions this month
... A27: 23 | B27: Issue management P&L pack to leadership | C27: Finance Manager | D27: 03-Apr | E27: ✅ Complete | F27: Pack circulated to CEO, CFO, and department heads on 3-Apr
A29: Close Completion: 22/23 tasks ✅

Sheet Management Summary
A1: TechServe India Pvt Ltd | Monthly Management Report | March 2025
A2: Prepared by: Finance Operations Team | Distribution: CFO, CEO, Department Heads | Classification: Confidential
A4: KEY PERFORMANCE INDICATORS — MARCH 2025
A5: KPI | B5: Budget | C5: Actuals | D5: Variance | E5: Status
A6: Total Revenue (₹) | B6: ₹1,35,00,000 | C6: ₹1,31,50,000 | D6: ▼ ₹3,50,000 (2.6%) | E6: 🟡 Near Miss
A7: Gross Profit Margin | B7: 60.4% | C7: 56.1% | D7: ▼ 4.3 pp | E7: 🔴 Below Target
A8: EBITDA Margin | B8: 49.3% | C8: 43.5% | D8: ▼ 5.8 pp | E8: 🔴 Below Target
A9: PAT (₹) | B9: ₹12,00,000 | C9: ₹9,80,000 | D9: ▼ ₹2,20,000 (18.3%) | E9: 🔴 Below Target
A10: Headcount (Billable) | B10: 21 | C10: 22 | D10: ▲ 1 (contract hire) | E10: 🟡 Approved
A11: DSO (Days Sales Outst.) | B11: 45 days | C11: 51 days | D11: ▲ 6 days | E11: 🔴 Watch List
A12: Close Cycle Time | B12: T+3 days | C12: T+2 days | D12: ▲ 1 day ahead | E12: 🟢 Excellent
A15: 3 KEY TAKEAWAYS FOR MANAGEMENT — MARCH 2025
A16: TAKEAWAY 1: Revenue Shortfall is Timing, Not Demand
A17: Export revenue of ₹4.20L was delayed by 2 business days (invoiced 1-Apr) due to client approval cycles. Domestic pipeline remains strong with 3 active RFPs worth ₹48L. Recommend: tighten billing calendar — all invoices to be raised by 25th of each month.
A18: TAKEAWAY 2: Salary Cost Overrun Requires Structural Fix
A19: Total salary cost (delivery + admin) exceeded budget by ₹3.50L (approx. 8%). One-time retention bonus (₹2.0L) and mid-month contract hire (₹2.0L) were both management-approved but not reflected in the budget. Recommend: introduce a supplementary budget approval process for off-cycle hires and bonuses to maintain forecast accuracy.
A20: TAKEAWAY 3: DSO Deterioration Needs Immediate AR Action
A21: Days Sales Outstanding has stretched to 51 days vs 45-day target — a 13% increase. Top 2 customers (representing ₹9.2L of AR) have payments overdue by 18–22 days. Recommend: Finance Analyst to issue formal dunning letters by 5-Apr; escalate to BD if no response within 7 days.
A23: CFO ACTION ITEMS — APRIL 2025
A24: # | B24: Action Required | C24: Owner | D24: Due Date
A25: 1 | B25: Approve supplementary budget for Q1 contract hires — ₹6.0L allocation requested | C25: Finance Analyst | D25: 10-Apr
A26: 2 | B26: Review and sign DSO escalation letter to Top 2 customers | C26: CFO / BD Head | D26: 05-Apr
A27: 3 | B27: Approve advance tax deposit challan — ₹2.80L TDS payable | C27: CFO | D27: 07-Apr
A28: 4 | B28: Greenlight FY26 salary revision projections for budget reforecast | C28: CFO / HR | D28: 15-Apr
A29: 5 | B29: Resolve GST ITC mismatch of ₹18,000 — vendor clarification pending | C29: Tax Analyst | D29: 12-Apr

Sheet 6-Month Trend
A1: TechServe India Pvt Ltd — 6-Month Financial Trend (Oct 2024 – Mar 2025)
A3: Metric | B3: Oct-24 | C3: Nov-24 | D3: Dec-24 | E3: Jan-25 | F3: Feb-25 | G3: Mar-25 | H3: Trend
A4: Revenue (₹) | B4: 11200000 | C4: 12500000 | D4: 14800000 | E4: 12100000 | F4: 13800000 | G4: 13150000 | H4: ▼ -4.7%
A5: Gross Profit (₹) | B5: 6720000 | C5: 7625000 | D5: 9104000 | E5: 7381000 | F5: 8418000 | G5: 7380000 | H5: ▼ -12.3%
A6: Gross Margin % | B6: 0.6 | C6: 0.61 | D6: 0.615 | E6: 0.61 | F6: 0.61 | G6: 0.561 | H6: ▼ -4.9pp
A7: EBITDA (₹) | B7: 5040000 | C7: 5875000 | D7: 7104000 | E7: 5445000 | F7: 6624000 | G7: 5715000 | H7: ▼ -13.7%
A8: EBITDA Margin % | B8: 0.45 | C8: 0.47 | D8: 0.48 | E8: 0.45 | F8: 0.48 | G8: 0.435 | H8: ▼ -4.5pp
A9: PAT (₹) | B9: 1050000 | C9: 1200000 | D9: 1750000 | E9: 1100000 | F9: 1380000 | G9: 980000 | H9: ▼ -29.0%
A10: PAT Margin % | B10: 0.094 | C10: 0.096 | D10: 0.118 | E10: 0.091 | F10: 0.1 | G10: 0.075 | H10: ▼ -2.5pp
A11: Headcount (Total) | B11: 28 | C11: 29 | D11: 30 | E11: 30 | F11: 31 | G11: 32 | H11: ▲ +3.2%
A12: Revenue per Head (₹) | B12: 400000 | C12: 431034 | D12: 493333 | E12: 403333 | F12: 445161 | G12: 410938 | H12: ▼ -7.7%
A13: DSO (Days) | B13: 42 | C13: 44 | D13: 40 | E13: 47 | F13: 45 | G13: 51 | H13: ▲ +13.3%
